tessif_fine_2_2_2/__init__.py
tessif_fine_2_2_2/optimize.py
tessif_fine_2_2_2/post_process.py
tessif_fine_2_2_2/transform.py
tessif_fine_2_2_2-0.1.3.dist-info/LICENSE
tessif_fine_2_2_2-0.1.3.dist-info/WHEEL
tessif_fine_2_2_2-0.1.3.dist-info/METADATA
tessif_fine_2_2_2-0.1.3.dist-info/RECORD
