Metadata-Version: 2.1
Name: tessif-fine-2-2-2
Version: 0.1.3
Summary: Tessif-Plugin for providing FINE 2.2.2 support.
Home-page: https://github.com/tZ3ma/tessif_fine_2_2_2
License: MIT
Keywords: Tessif,Tessif-FiNE,ESSMOS,optimization,energy supply system modelling
Author: Mathias Ammon
Author-email: tz3ma.coding@use.startmail.com
Requires-Python: >=3.8,<3.9
Classifier: License :: OSI Approved :: MIT License
Classifier: Programming Language :: Python :: 3
Classifier: Programming Language :: Python :: 3.8
Requires-Dist: fine (==2.2.2)
Requires-Dist: tessif (>=0.0.25)
Project-URL: Repository, https://github.com/tZ3ma/tessif_fine_2_2_2
